{
  "serviceTypes": {
    "org.myrobotlab.service.Adafruit16CServoDriver": {
      "name": "org.myrobotlab.service.Adafruit16CServoDriver",
      "description": "Adafruit Motor Shield Service",
      "dependencies": [
        "com.adafruit.servodriver"
      ]
    },
    "org.myrobotlab.service.AdafruitMotorShield": {
      "name": "org.myrobotlab.service.AdafruitMotorShield",
      "description": "Adafruit Motor Shield Service",
      "dependencies": [
        "com.adafruit.motorshield"
      ]
    },
    "org.myrobotlab.service.Arduino": {
      "name": "org.myrobotlab.service.Arduino",
      "description": "This service interfaces with an Arduino micro-controller.",
      "dependencies": [
        "cc.arduino",
        "gnu.io.rxtx",
        "org.fife.rsyntaxtextarea"
      ]
    },
    "org.myrobotlab.service.Arm": {
      "name": "org.myrobotlab.service.Arm"
    },
    "org.myrobotlab.service.AudioCapture": {
      "name": "org.myrobotlab.service.AudioCapture",
      "description": "captures and stores audio from microphone"
    },
    "org.myrobotlab.service.AudioFile": {
      "name": "org.myrobotlab.service.AudioFile",
      "description": "Plays back audio file. Can block or multi-thread play",
      "dependencies": [
        "javazoom.jl.player"
      ]
    },
    "org.myrobotlab.service.BeagleBoardBlack": {
      "name": "org.myrobotlab.service.BeagleBoardBlack",
      "description": "service to access the beagle board black hardware"
    },
    "org.myrobotlab.service.Blender": {
      "name": "org.myrobotlab.service.Blender",
      "description": "used as a general blender"
    },
    "org.myrobotlab.service.ChessGame": {
      "name": "org.myrobotlab.service.ChessGame",
      "description": "used to generate pulses",
      "dependencies": [
        "org.op.chess"
      ]
    },
    "org.myrobotlab.service.CleverBot": {
      "name": "org.myrobotlab.service.CleverBot",
      "description": "used as a general template",
      "dependencies": [
        "com.googlecode.chatterbot"
      ]
    },
    "org.myrobotlab.service.Clock": {
      "name": "org.myrobotlab.service.Clock",
      "description": "used to generate pulses"
    },
    "org.myrobotlab.service.Cortex": {
      "name": "org.myrobotlab.service.Cortex",
      "description": "used as a general template"
    },
    "org.myrobotlab.service.Cron": {
      "name": "org.myrobotlab.service.Cron",
      "description": "A Cron like service capable of scheduling future actions",
      "dependencies": [
        "it.sauronsoftware.cron4j"
      ]
    },
    "org.myrobotlab.service.Drupal": {
      "name": "org.myrobotlab.service.Drupal",
      "description": "used as a general template"
    },
    "org.myrobotlab.service.GPS": {
      "name": "org.myrobotlab.service.GPS",
      "description": "The GPS service"
    },
    "org.myrobotlab.service.GUIService": {
      "name": "org.myrobotlab.service.GUIService",
      "description": "<html>Service used to graphically display and control other services</html>"
    },
    "org.myrobotlab.service.GoogleSTT": {
      "name": "org.myrobotlab.service.GoogleSTT",
      "description": "Uses the Google Speech To Text service",
      "dependencies": [
        "javaFlacEncoder.FLAC_FileEncoder",
        "org.tritonus.share.sampled.floatsamplebuffer"
      ]
    },
    "org.myrobotlab.service.Graphics": {
      "name": "org.myrobotlab.service.Graphics",
      "description": "a graphics service encapsulating Java swing graphic methods"
    },
    "org.myrobotlab.service.HTTPClient": {
      "name": "org.myrobotlab.service.HTTPClient",
      "description": "an HTTP client, used to fetch information on the web",
      "dependencies": [
        "org.apache.commons.httpclient"
      ]
    },
    "org.myrobotlab.service.Houston": {
      "name": "org.myrobotlab.service.Houston",
      "description": "used as a general template"
    },
    "org.myrobotlab.service.IPCamera": {
      "name": "org.myrobotlab.service.IPCamera",
      "description": "used as a general template",
      "dependencies": [
        "com.googlecode.javacv"
      ]
    },
    "org.myrobotlab.service.InMoov": {
      "name": "org.myrobotlab.service.InMoov",
      "description": "The InMoov service"
    },
    "org.myrobotlab.service.InMoovArm": {
      "name": "org.myrobotlab.service.InMoovArm",
      "description": "the InMoov Arm Service"
    },
    "org.myrobotlab.service.InMoovGestureCreator": {
      "name": "org.myrobotlab.service.InMoovGestureCreator",
      "description": "an easier way to create gestures for InMoov"
    },
    "org.myrobotlab.service.InMoovHand": {
      "name": "org.myrobotlab.service.InMoovHand",
      "description": "hand service for inmoov"
    },
    "org.myrobotlab.service.InMoovHead": {
      "name": "org.myrobotlab.service.InMoovHead",
      "description": "InMoov Head Service"
    },
    "org.myrobotlab.service.InMoovTorso": {
      "name": "org.myrobotlab.service.InMoovTorso",
      "description": "the InMoov Arm Service"
    },
    "org.myrobotlab.service.Incubator": {
      "name": "org.myrobotlab.service.Incubator",
      "description": "used as a general template"
    },
    "org.myrobotlab.service.InverseKinematics": {
      "name": "org.myrobotlab.service.InverseKinematics",
      "description": "used as a general template"
    },
    "org.myrobotlab.service.JFugue": {
      "name": "org.myrobotlab.service.JFugue",
      "description": "service wrapping Jfugue - http://www.jfugue.org/ used for music and sound generation",
      "dependencies": [
        "org.jfugue.music"
      ]
    },
    "org.myrobotlab.service.Joystick": {
      "name": "org.myrobotlab.service.Joystick",
      "description": "used for interfacing with a Joystick",
      "dependencies": [
        "net.java.games.jinput"
      ]
    },
    "org.myrobotlab.service.Keyboard": {
      "name": "org.myrobotlab.service.Keyboard",
      "description": "keyboard"
    },
    "org.myrobotlab.service.LeapMotion2": {
      "name": "org.myrobotlab.service.LeapMotion2",
      "description": "LeapMotion service",
      "dependencies": [
        "com.leapmotion"
      ]
    },
    "org.myrobotlab.service.Log": {
      "name": "org.myrobotlab.service.Log",
      "description": "logging service"
    },
    "org.myrobotlab.service.MQTT": {
      "name": "org.myrobotlab.service.MQTT",
      "description": "This is an MQTT client based on the Paho MQTT client library. MQTT is a machine-to-machine (M2M)/'Internet of Things' connectivity protocol. See http://mqtt.org",
      "dependencies": [
        "org.eclipse.paho"
      ]
    },
    "org.myrobotlab.service.Motor": {
      "name": "org.myrobotlab.service.Motor",
      "description": "general motor service"
    },
    "org.myrobotlab.service.MouthControl": {
      "name": "org.myrobotlab.service.MouthControl",
      "description": "mouth movements based on spoken text"
    },
    "org.myrobotlab.service.OpenCV": {
      "name": "org.myrobotlab.service.OpenCV",
      "description": "OpenCV (computer vision) service wrapping many of the functions and filters of OpenCV. ",
      "dependencies": [
        "com.googlecode.javacv",
        "net.sourceforge.opencv"
      ]
    },
    "org.myrobotlab.service.OpenNI": {
      "name": "org.myrobotlab.service.OpenNI",
      "description": "OpenNI Service",
      "dependencies": [
        "com.googlecode.simpleopenni"
      ]
    },
    "org.myrobotlab.service.PID": {
      "name": "org.myrobotlab.service.PID",
      "description": "<html>a PID control service from<br>http://brettbeauregard.com/blog/2011/04/improving-the-beginners-pid-introduction/</html>"
    },
    "org.myrobotlab.service.PID2": {
      "name": "org.myrobotlab.service.PID2",
      "description": "<html>a PID2 control service from<br>http://brettbeauregard.com/blog/2011/04/improving-the-beginners-pid-introduction/</html>"
    },
    "org.myrobotlab.service.ParallelPort": {
      "name": "org.myrobotlab.service.ParallelPort",
      "description": "<html>(not working yet) used to communicate to and from the parallel port<br>wrapping the great project http://rxtx.qbang.org/ using LGPL v 2.1</html>",
      "dependencies": [
        "gnu.io.rxtx"
      ]
    },
    "org.myrobotlab.service.PickToLight": {
      "name": "org.myrobotlab.service.PickToLight",
      "description": "Pick to light system",
      "dependencies": [
        "org.apache.commons.httpclient",
        "com.pi4j.pi4j"
      ]
    },
    "org.myrobotlab.service.Pingdar": {
      "name": "org.myrobotlab.service.Pingdar",
      "description": "used as a ultra sonic radar"
    },
    "org.myrobotlab.service.Plantoid": {
      "name": "org.myrobotlab.service.Plantoid",
      "description": "the plantoid service"
    },
    "org.myrobotlab.service.PlayerStage": {
      "name": "org.myrobotlab.service.PlayerStage",
      "description": "stubbed out for Player Stage - partially implemented"
    },
    "org.myrobotlab.service.ProgramAB": {
      "name": "org.myrobotlab.service.ProgramAB",
      "description": "AIML 2.0 Reference interpreter based on Program AB",
      "dependencies": [
        "org.alicebot.ab"
      ]
    },
    "org.myrobotlab.service.Propeller": {
      "name": "org.myrobotlab.service.Propeller",
      "description": "<html>Propeller is a service which interfaces with an Propeller micro-controller.<br>This interface can operate over radio, IR, or other communications,<br>but and appropriate .PDE file must be loaded into the micro-controller.<br>See http://myrobotlab.org/communication for details",
      "dependencies": [
        "org.alicebot.ab"
      ]
    },
    "org.myrobotlab.service.Proxy": {
      "name": "org.myrobotlab.service.Proxy",
      "description": "a Proxy service capable of proxying classes which can not or should not be created"
    },
    "org.myrobotlab.service.Python": {
      "name": "org.myrobotlab.service.Python",
      "description": "Python IDE",
      "dependencies": [
        "org.python.core",
        "org.fife.autocomplete",
        "org.fife.rsyntaxtextarea"
      ]
    },
    "org.myrobotlab.service.ROS": {
      "name": "org.myrobotlab.service.ROS",
      "description": "used as a general template"
    },
    "org.myrobotlab.service.RasPi": {
      "name": "org.myrobotlab.service.RasPi",
      "description": "Raspberry Pi service used for accessing specific RasPi hardware such as I2C",
      "dependencies": [
        "com.pi4j.pi4j"
      ]
    },
    "org.myrobotlab.service.Red5": {
      "name": "org.myrobotlab.service.Red5",
      "description": "Red5 video/audio streaming service"
    },
    "org.myrobotlab.service.RemoteAdapter": {
      "name": "org.myrobotlab.service.RemoteAdapter",
      "description": "allows remote communication between applets, or remote instances of myrobotlab"
    },
    "org.myrobotlab.service.RobotPlatform": {
      "name": "org.myrobotlab.service.RobotPlatform",
      "description": "<html>used to encapsulate many of the functions and formulas regarding 2 motor platforms.<br>encoders and other feedback mechanisms can be added to provide heading, location and other information</html>"
    },
    "org.myrobotlab.service.Roomba": {
      "name": "org.myrobotlab.service.Roomba",
      "description": "used as a general template",
      "dependencies": [
        "gnu.io.rxtx"
      ]
    },
    "org.myrobotlab.service.Runtime": {
      "name": "org.myrobotlab.service.Runtime",
      "description": "Runtime singleton service"
    },
    "org.myrobotlab.service.SLAMBad": {
      "name": "org.myrobotlab.service.SLAMBad",
      "description": "used as a general template",
      "dependencies": [
        "javax.vecmath",
        "com.sun.java3d"
      ]
    },
    "org.myrobotlab.service.Sabertooth": {
      "name": "org.myrobotlab.service.Sabertooth",
      "description": "used as a general template",
      "dependencies": [
        "gnu.io.rxtx"
      ]
    },
    "org.myrobotlab.service.Security": {
      "name": "org.myrobotlab.service.Security",
      "description": "security service"
    },
    "org.myrobotlab.service.SensorMonitor": {
      "name": "org.myrobotlab.service.SensorMonitor",
      "description": "<html>sensor monitor - capable of displaying sensor information in a crude oscilliscope fasion</html>"
    },
    "org.myrobotlab.service.Serial": {
      "name": "org.myrobotlab.service.Serial",
      "description": "reads and writes serial data",
      "dependencies": [
        "gnu.io.rxtx"
      ]
    },
    "org.myrobotlab.service.Servo": {
      "name": "org.myrobotlab.service.Servo",
      "description": "basic servo service"
    },
    "org.myrobotlab.service.ServoOrchestrator": {
      "name": "org.myrobotlab.service.ServoOrchestrator",
      "description": "organize your Servo-movements"
    },
    "org.myrobotlab.service.Shoutbox": {
      "name": "org.myrobotlab.service.Shoutbox",
      "description": "shoutbox server for myrobotlab"
    },
    "org.myrobotlab.service.SoccerGame": {
      "name": "org.myrobotlab.service.SoccerGame",
      "description": "robot soccer"
    },
    "org.myrobotlab.service.Solr": {
      "name": "org.myrobotlab.service.Solr",
      "description": "Solr Service - Open source search engine."
    },
    "org.myrobotlab.service.Speech": {
      "name": "org.myrobotlab.service.Speech",
      "description": "speech synthesis service",
      "dependencies": [
        "com.sun.speech.freetts",
        "org.apache.commons.httpclient",
        "javazoom.jl.player"
      ]
    },
    "org.myrobotlab.service.Sphinx": {
      "name": "org.myrobotlab.service.Sphinx",
      "description": "<html>speech recoginition service wrapping Sphinx 4</html>",
      "dependencies": [
        "javax.speech.recognition",
        "edu.cmu.sphinx"
      ]
    },
    "org.myrobotlab.service.Stepper": {
      "name": "org.myrobotlab.service.Stepper",
      "description": "general motor service"
    },
    "org.myrobotlab.service.Sweety": {
      "name": "org.myrobotlab.service.Sweety",
      "description": "Service for the robot Sweety"
    },
    "org.myrobotlab.service.TesseractOCR": {
      "name": "org.myrobotlab.service.TesseractOCR",
      "description": "Tesseract OCR Engine",
      "dependencies": [
        "net.sourceforge.tess4j",
        "com.sun.jna"
      ]
    },
    "org.myrobotlab.service.ThingSpeak": {
      "name": "org.myrobotlab.service.ThingSpeak",
      "description": "used as a general template"
    },
    "org.myrobotlab.service.TopCodes": {
      "name": "org.myrobotlab.service.TopCodes",
      "description": "used as a general topcodes",
      "dependencies": [
        "edu.northwestern.topcodes"
      ]
    },
    "org.myrobotlab.service.Tracking": {
      "name": "org.myrobotlab.service.Tracking",
      "description": "proportional control, tracking, and translation"
    },
    "org.myrobotlab.service.TweedleBot": {
      "name": "org.myrobotlab.service.TweedleBot",
      "description": "<html>used to encapsulate many of the functions and formulas regarding 2 motor platforms.<br>encoders and other feedback mechanisms can be added to provide heading, location and other information</html>"
    },
    "org.myrobotlab.service.Twitter": {
      "name": "org.myrobotlab.service.Twitter",
      "description": "used as a general template",
      "dependencies": [
        "org.twitter4j.twitter"
      ]
    },
    "org.myrobotlab.service.UltrasonicSensor": {
      "name": "org.myrobotlab.service.UltrasonicSensor",
      "description": "used as a general template"
    },
    "org.myrobotlab.service.VideoStreamer": {
      "name": "org.myrobotlab.service.VideoStreamer",
      "description": "used as a general template"
    },
    "org.myrobotlab.service.WebGUI": {
      "name": "org.myrobotlab.service.WebGUI",
      "description": "The new web enabled GUIService 2.0 !",
      "dependencies": [
        "org.java_websocket.websocket"
      ]
    },
    "org.myrobotlab.service.Wii": {
      "name": "org.myrobotlab.service.Wii",
      "description": "<html>wrapper service for wiiusej</html>",
      "dependencies": [
        "wiiuse.wiimote"
      ]
    },
    "org.myrobotlab.service.WolframAlpha": {
      "name": "org.myrobotlab.service.WolframAlpha",
      "description": "Wolfram Alpha Service",
      "dependencies": [
        "com.wolfram.alpha",
        "org.apache.commons.httpclient"
      ]
    },
    "org.myrobotlab.service.XMPP": {
      "name": "org.myrobotlab.service.XMPP",
      "description": "xmpp service to access the jabber network",
      "dependencies": [
        "org.jivesoftware.smack"
      ]
    }
  },
  "categoryTypes": {
    "actuators": {
      "name": "actuators",
      "description": "motion controllers",
      "serviceTypes": [
        "org.myrobotlab.service.Motor",
        "org.myrobotlab.service.Servo",
        "org.myrobotlab.service.MouthControl",
        "org.myrobotlab.service.PID"
      ]
    },
    "audio": {
      "name": "audio",
      "description": "",
      "serviceTypes": [
        "org.myrobotlab.service.AudioCapture",
        "org.myrobotlab.service.AudioFile",
        "org.myrobotlab.service.JFugue"
      ]
    },
    "communication": {
      "name": "communication",
      "description": "allow communication to extrnal or remote devices",
      "serviceTypes": [
        "org.myrobotlab.service.RemoteAdapter",
        "org.myrobotlab.service.XMPP",
        "org.myrobotlab.service.Serial",
        "org.myrobotlab.service.ParallelPort",
        "org.myrobotlab.service.HTTPClient",
        "org.myrobotlab.service.WebGUI"
      ]
    },
    "control": {
      "name": "control",
      "description": "",
      "serviceTypes": [
        "org.myrobotlab.service.Keyboard",
        "org.myrobotlab.service.Joystick",
        "org.myrobotlab.service.InverseKinematics",
        "org.myrobotlab.service.PID",
        "org.myrobotlab.service.PickToLight",
        "org.myrobotlab.service.PID2"
      ]
    },
    "display": {
      "name": "display",
      "description": "",
      "serviceTypes": [
        "org.myrobotlab.service.GUIService",
        "org.myrobotlab.service.WebGUI",
        "org.myrobotlab.service.Log",
        "org.myrobotlab.service.VideoStreamer",
        "org.myrobotlab.service.ThingSpeak",
        "org.myrobotlab.service.OpenCV"
      ]
    },
    "intelligence": {
      "name": "intelligence",
      "description": "",
      "serviceTypes": [
        "org.myrobotlab.service.CleverBot",
        "org.myrobotlab.service.ChessGame",
        "org.myrobotlab.service.ProgramAB",
        "org.myrobotlab.service.TesseractOCR",
        "org.myrobotlab.service.WolframAlpha"
      ]
    },
    "microcontroller": {
      "name": "microcontroller",
      "description": "",
      "serviceTypes": [
        "org.myrobotlab.service.Arduino",
        "org.myrobotlab.service.BeagleBoardBlack",
        "org.myrobotlab.service.Propeller",
        "org.myrobotlab.service.RasPi"
      ]
    },
    "motors": {
      "name": "motors",
      "description": "",
      "serviceTypes": [
        "org.myrobotlab.service.AdafruitMotorShield",
        "org.myrobotlab.service.Motor",
        "org.myrobotlab.service.Stepper"
      ]
    },
    "programming": {
      "name": "programming",
      "description": "",
      "serviceTypes": [
        "org.myrobotlab.service.Python",
        "org.myrobotlab.service.GUIService"
      ]
    },
    "robots": {
      "name": "robots",
      "description": "",
      "serviceTypes": [
        "org.myrobotlab.service.Houston",
        "org.myrobotlab.service.InMoov",
        "org.myrobotlab.service.InMoovHead",
        "org.myrobotlab.service.InMoovHand",
        "org.myrobotlab.service.InMoovArm",
        "org.myrobotlab.service.InMoovTorso",
        "org.myrobotlab.service.InMoovGestureCreator",
        "org.myrobotlab.service.Plantoid",
        "org.myrobotlab.service.Roomba"
      ]
    },
    "security": {
      "name": "security",
      "description": "",
      "serviceTypes": [
        "org.myrobotlab.service.Security"
      ]
    },
    "sensors": {
      "name": "sensors",
      "description": "",
      "serviceTypes": [
        "org.myrobotlab.service.Arduino",
        "org.myrobotlab.service.SensorMonitor",
        "org.myrobotlab.service.UltrasonicSensor",
        "org.myrobotlab.service.Wii"
      ]
    },
    "shields": {
      "name": "shields",
      "description": "",
      "serviceTypes": [
        "org.myrobotlab.service.ACEduinoMotorShield",
        "org.myrobotlab.service.Adafruit16CServoDriver",
        "org.myrobotlab.service.AdafruitMotorShield"
      ]
    },
    "simulators": {
      "name": "simulators",
      "description": "",
      "serviceTypes": [
        "org.myrobotlab.service.SLAMBad"
      ]
    },
    "social": {
      "name": "social",
      "description": "",
      "serviceTypes": [
        "org.myrobotlab.service.Twitter",
        "org.myrobotlab.service.Shoutbox",
        "org.myrobotlab.service.CleverBot"
      ]
    },
    "speech recognition": {
      "name": "speech recognition",
      "description": "",
      "serviceTypes": [
        "org.myrobotlab.service.Sphinx",
        "org.myrobotlab.service.AndroidVoiceRecognition",
        "org.myrobotlab.service.GoogleSTT"
      ]
    },
    "speech synthesis": {
      "name": "speech synthesis",
      "description": "",
      "serviceTypes": [
        "org.myrobotlab.service.Speech"
      ]
    },
    "timers": {
      "name": "timers",
      "description": "",
      "serviceTypes": [
        "org.myrobotlab.service.Clock",
        "org.myrobotlab.service.Cron"
      ]
    },
    "vision": {
      "name": "vision",
      "description": "",
      "serviceTypes": [
        "org.myrobotlab.service.Cortex",
        "org.myrobotlab.service.OpenCV",
        "org.myrobotlab.service.OpenNI",
        "org.myrobotlab.service.IPCamera",
        "org.myrobotlab.service.Tracking",
        "org.myrobotlab.service.TopCodes"
      ]
    },
    "search engine": {
      "name": "search engine",
      "description": "",
      "serviceTypes": [
        "org.myrobotlab.service.SolrService"
      ]
    }
  },
  "dependencyTypes": {
    "be.hogent.tarsos": {
      "org": "be.hogent.tarsos",
      "revision": "1.7",
      "resolved": false,
      "released": true
    },
    "cc.arduino": {
      "org": "cc.arduino",
      "revision": "1.0",
      "resolved": false,
      "released": true
    },
    "com.adafruit.motorshield": {
      "org": "com.adafruit.motorshield",
      "revision": "1.0",
      "resolved": false,
      "released": true
    },
    "com.adafruit.servodriver": {
      "org": "com.adafruit.servodriver",
      "revision": "1.0",
      "resolved": false,
      "released": true
    },
    "com.centralnexus.joystick": {
      "org": "com.centralnexus.joystick",
      "revision": "0.7",
      "resolved": false,
      "released": true
    },
    "com.getflourish.googlestt": {
      "org": "com.getflourish.googlestt",
      "revision": "1.0",
      "resolved": false,
      "released": true
    },
    "com.github.recognito": {
      "org": "com.github.recognito",
      "revision": "0.1.0",
      "resolved": false,
      "released": true
    },
    "com.goodrobots": {
      "org": "com.goodrobots",
      "revision": "1.0.2-SNAPSHOT",
      "resolved": false,
      "released": true
    },
    "com.google.gson": {
      "org": "com.google.gson",
      "revision": "2.3.1",
      "resolved": false,
      "released": true
    },
    "com.googlecode.chatterbot": {
      "org": "com.googlecode.chatterbot",
      "revision": "1.2.1",
      "resolved": false,
      "released": true
    },
    "com.googlecode.javacv": {
      "org": "com.googlecode.javacv",
      "revision": "0.6",
      "resolved": false,
      "released": true
    },
    "com.googlecode.jssc": {
      "org": "com.googlecode.jssc",
      "revision": "0.9.0",
      "resolved": false,
      "released": true
    },
    "com.googlecode.simpleopenni": {
      "org": "com.googlecode.simpleopenni",
      "revision": "1.96",
      "resolved": false,
      "released": true
    },
    "com.leapmotion": {
      "org": "com.leapmotion",
      "revision": "2.1.3",
      "resolved": false,
      "released": true
    },
    "com.mxgraph.jgraph": {
      "org": "com.mxgraph.jgraph",
      "revision": "1.6.1.2",
      "resolved": false,
      "released": true
    },
    "com.oracle.mysql": {
      "org": "com.oracle.mysql",
      "revision": "5.1.32",
      "resolved": false,
      "released": true
    },
    "com.pi4j.pi4j": {
      "org": "com.pi4j.pi4j",
      "revision": "0.0.5",
      "resolved": false,
      "released": true
    },
    "com.strobel.decompiler": {
      "org": "com.strobel.decompiler",
      "revision": "0.3.2",
      "resolved": false,
      "released": true
    },
    "com.sun.java3d": {
      "org": "com.sun.java3d",
      "revision": "1.5.1",
      "resolved": false,
      "released": true
    },
    "com.sun.jna": {
      "org": "com.sun.jna",
      "revision": "3.2.2",
      "resolved": false,
      "released": true
    },
    "com.sun.mail": {
      "org": "com.sun.mail",
      "revision": "1.4.5",
      "resolved": false,
      "released": true
    },
    "com.sun.speech.freetts": {
      "org": "com.sun.speech.freetts",
      "revision": "1.2",
      "resolved": false,
      "released": true
    },
    "com.wolfram.alpha": {
      "org": "com.wolfram.alpha",
      "revision": "1.1",
      "resolved": false,
      "released": true
    },
    "edu.cmu.sphinx": {
      "org": "edu.cmu.sphinx",
      "revision": "4-1.0beta6",
      "resolved": false,
      "released": true
    },
    "edu.northwestern.topcodes": {
      "org": "edu.northwestern.topcodes",
      "revision": "1.0",
      "resolved": false,
      "released": true
    },
    "gnu.io.rxtx": {
      "org": "gnu.io.rxtx",
      "revision": "2.1-7r2",
      "resolved": false,
      "released": true
    },
    "io.netty": {
      "org": "io.netty",
      "revision": "4.0.19",
      "resolved": false,
      "released": true
    },
    "it.sauronsoftware.cron4j": {
      "org": "it.sauronsoftware.cron4j",
      "revision": "2.2.5",
      "resolved": false,
      "released": true
    },
    "javaFlacEncoder.FLAC_FileEncoder": {
      "org": "javaFlacEncoder.FLAC_FileEncoder",
      "revision": "0.1",
      "resolved": false,
      "released": true
    },
    "javaclient3.playerstage": {
      "org": "javaclient3.playerstage",
      "revision": "3",
      "resolved": false,
      "released": true
    },
    "javax.microedition.io": {
      "org": "javax.microedition.io",
      "revision": "2.0.3",
      "resolved": false,
      "released": true
    },
    "javax.speech.recognition": {
      "org": "javax.speech.recognition",
      "revision": "1.0",
      "resolved": false,
      "released": true
    },
    "javax.vecmath": {
      "org": "javax.vecmath",
      "revision": "1.5.1",
      "resolved": false,
      "released": true
    },
    "javazoom.jl.player": {
      "org": "javazoom.jl.player",
      "revision": "1.0.1",
      "resolved": false,
      "released": true
    },
    "javazoom.spi": {
      "org": "javazoom.spi",
      "revision": "1.9.5",
      "resolved": false,
      "released": true
    },
    "net.java.games.jinput": {
      "org": "net.java.games.jinput",
      "revision": "20120914",
      "resolved": false,
      "released": true
    },
    "net.sourceforge.opencv": {
      "org": "net.sourceforge.opencv",
      "revision": "2.4.6",
      "resolved": false,
      "released": true
    },
    "net.sourceforge.simbad": {
      "org": "net.sourceforge.simbad",
      "revision": "1.4",
      "resolved": false,
      "released": true
    },
    "net.sourceforge.tess4j": {
      "org": "net.sourceforge.tess4j",
      "revision": "1.1",
      "resolved": false,
      "released": true
    },
    "org.alicebot.ab": {
      "org": "org.alicebot.ab",
      "revision": "0.0.6.26",
      "resolved": false,
      "released": true
    },
    "org.apache.commons.httpclient": {
      "org": "org.apache.commons.httpclient",
      "revision": "4.2.5",
      "resolved": false,
      "released": true
    },
    "org.apache.ivy": {
      "org": "org.apache.ivy",
      "revision": "2.4.0-rc1",
      "resolved": false,
      "released": true
    },
    "org.apache.log4j": {
      "org": "org.apache.log4j",
      "revision": "1.2.14",
      "resolved": false,
      "released": true
    },
    "org.apache.solr": {
      "org": "org.apache.solr",
      "revision": "4.10.2",
      "resolved": false,
      "released": true
    },
    "org.drjava.java": {
      "org": "org.drjava.java",
      "revision": "20120818",
      "resolved": false,
      "released": true
    },
    "org.eclipse.paho": {
      "org": "org.eclipse.paho",
      "revision": "1.0",
      "resolved": false,
      "released": true
    },
    "org.fife.autocomplete": {
      "org": "org.fife.autocomplete",
      "revision": "2.0.4",
      "resolved": false,
      "released": true
    },
    "org.fife.rsyntaxtextarea": {
      "org": "org.fife.rsyntaxtextarea",
      "revision": "2.0.4.1",
      "resolved": false,
      "released": true
    },
    "org.java_websocket.websocket": {
      "org": "org.java_websocket.websocket",
      "revision": "1.2",
      "resolved": false,
      "released": true
    },
    "org.jfugue.music": {
      "org": "org.jfugue.music",
      "revision": "4.0.3",
      "resolved": false,
      "released": true
    },
    "org.jivesoftware.smack": {
      "org": "org.jivesoftware.smack",
      "revision": "3.3.0",
      "resolved": false,
      "released": true
    },
    "org.jsoup": {
      "org": "org.jsoup",
      "revision": "1.7.3",
      "resolved": false,
      "released": true
    },
    "org.junit": {
      "org": "org.junit",
      "revision": "4.11",
      "resolved": false,
      "released": true
    },
    "org.myrobotlab.service.incubator": {
      "org": "org.myrobotlab.service.incubator",
      "revision": "1.0",
      "resolved": false,
      "released": true
    },
    "org.op.chess": {
      "org": "org.op.chess",
      "revision": "1.0.0",
      "resolved": false,
      "released": true
    },
    "org.processing": {
      "org": "org.processing",
      "revision": "unknown",
      "resolved": false,
      "released": true
    },
    "org.python.core": {
      "org": "org.python.core",
      "revision": "2.5.2",
      "resolved": false,
      "released": true
    },
    "org.saintandreas.jovr": {
      "org": "org.saintandreas.jovr",
      "revision": "0.3.2.4",
      "resolved": false,
      "released": true
    },
    "org.simpleframework.xml": {
      "org": "org.simpleframework.xml",
      "revision": "2.7",
      "resolved": false,
      "released": true
    },
    "org.slf4j": {
      "org": "org.slf4j",
      "revision": "1.6.1",
      "resolved": false,
      "released": true
    },
    "org.tritonus.share.sampled.floatsamplebuffer": {
      "org": "org.tritonus.share.sampled.floatsamplebuffer",
      "revision": "0.3.6",
      "resolved": false,
      "released": true
    },
    "org.twitter4j.twitter": {
      "org": "org.twitter4j.twitter",
      "revision": "3.0.5",
      "resolved": false,
      "released": true
    },
    "ph.com.alexan.aceduino": {
      "org": "ph.com.alexan.aceduino",
      "revision": "1.0",
      "resolved": false,
      "released": true
    },
    "se.comhem.chess": {
      "org": "se.comhem.chess",
      "revision": "1.1.2",
      "resolved": false,
      "released": true
    },
    "simbad.gui": {
      "org": "simbad.gui",
      "revision": "1.4",
      "resolved": false,
      "released": true
    },
    "wiiuse.wiimote": {
      "org": "wiiuse.wiimote",
      "revision": "0.12b",
      "resolved": false,
      "released": true
    }
  }
}